techzdl/__init__.py
techzdl/extra.py
techzdl/logger.py
techzdl-1.2.6.dist-info/LICENSE
techzdl-1.2.6.dist-info/METADATA
techzdl-1.2.6.dist-info/WHEEL
techzdl-1.2.6.dist-info/top_level.txt
techzdl-1.2.6.dist-info/RECORD
