Metadata-Version: 2.1
Name: techzdl
Version: 1.2.6
Summary: A simple yet powerfull file downloader package for python
Home-page: https://github.com/TechShreyash/techzdl
Author: TechShreyash
Author-email: techshreyash123@gmail.com
License: MIT
Classifier: Programming Language :: Python :: 3
Classifier: License :: OSI Approved :: MIT License
Classifier: Operating System :: OS Independent
Requires-Python: >=3.8
License-File: LICENSE
Requires-Dist: aiohttp
Requires-Dist: aiofiles
Requires-Dist: tqdm
Requires-Dist: curl-cffi
